MANIFEST.in
README.txt
setup.cfg
setup.py
docs/HISTORY.txt
docs/INSTALL.txt
docs/LICENSE.GPL
docs/LICENSE.txt
medialog/.DS_Store
medialog/__init__.py
medialog.fullpagetheme.egg-info/PKG-INFO
medialog.fullpagetheme.egg-info/SOURCES.txt
medialog.fullpagetheme.egg-info/dependency_links.txt
medialog.fullpagetheme.egg-info/entry_points.txt
medialog.fullpagetheme.egg-info/namespace_packages.txt
medialog.fullpagetheme.egg-info/not-zip-safe
medialog.fullpagetheme.egg-info/requires.txt
medialog.fullpagetheme.egg-info/top_level.txt
medialog/fullpagetheme/.DS_Store
medialog/fullpagetheme/__init__.py
medialog/fullpagetheme/configure.zcml
medialog/fullpagetheme/interfaces.py
medialog/fullpagetheme/version.txt
medialog/fullpagetheme/diazo_resources/.DS_Store
medialog/fullpagetheme/diazo_resources/README.txt
medialog/fullpagetheme/diazo_resources/favicon.ico
medialog/fullpagetheme/diazo_resources/index.html
medialog/fullpagetheme/diazo_resources/manifest.cfg
medialog/fullpagetheme/diazo_resources/preview.png
medialog/fullpagetheme/diazo_resources/rules.xml
medialog/fullpagetheme/diazo_resources/static/examples.css
medialog/fullpagetheme/diazo_resources/static/examples.js
medialog/fullpagetheme/diazo_resources/static/fullpage.css
medialog/fullpagetheme/diazo_resources/static/jquery.easings.min.js
medialog/fullpagetheme/diazo_resources/static/jquery.fullPage.css
medialog/fullpagetheme/diazo_resources/static/jquery.fullPage.js
medialog/fullpagetheme/diazo_resources/static/jquery.fullPage.min.js
medialog/fullpagetheme/diazo_resources/static/jquery.slimscroll.js
medialog/fullpagetheme/diazo_resources/static/jquery.slimscroll.min.js
medialog/fullpagetheme/diazo_resources/static/main.js
medialog/fullpagetheme/locales/README.txt
medialog/fullpagetheme/profiles/.DS_Store
medialog/fullpagetheme/profiles/default/browserlayer.xml
medialog/fullpagetheme/profiles/default/cssregistry.xml
medialog/fullpagetheme/profiles/default/jsregistry.xml
medialog/fullpagetheme/profiles/default/metadata.xml
medialog/fullpagetheme/profiles/default/theme.xml
medialog/fullpagetheme/template_overrides/.DS_Store
medialog/fullpagetheme/template_overrides/plone.app.collection.browser.templates.all_content.pt