Metadata-Version: 1.1
Name: medialog.fullpagetheme
Version: 0.2.1
Summary: FullpageTheme
Home-page: https://github.com/espenmn/medialog.fullpagetheme
Author: Espen Moe-Nilssen
Author-email: espen@medialog.no
License: GPL
Platform: UNKNOWN
Classifier: Framework :: Plone
Classifier: Programming Language :: Python
Classifier: Topic :: Software Development :: Libraries :: Python Modules
